sd_upload/module_1.py
sd_upload/module_2.py
sd_upload/module_3.py
sd_upload/upload.py
sd_upload/upload_v2.py
sd_upload-0.1.1.dist-info/METADATA
sd_upload-0.1.1.dist-info/WHEEL
sd_upload-0.1.1.dist-info/top_level.txt
sd_upload-0.1.1.dist-info/RECORD
