Metadata-Version: 2.1
Name: sd-upload
Version: 0.1.1
Summary: Package to upload files to the Robin Radar API
Home-page: https://bitbucket.org/robin-radar-systems/sd-api-upload-pip-package.git
Author: Tivadar Kamondy
Author-email: tivadar.kamondy@robinradar.com
License: MIT
Keywords: python
Platform: UNKNOWN
Requires-Dist: tqdm (>=4.62.0)
